atk_training_rin_chatlink/__init__.py
atk_training_rin_chatlink/auth_commands.py
atk_training_rin_chatlink/client_secrets.json
atk_training_rin_chatlink/main.py
atk_training_rin_chatlink/processing.py
atk_training_rin_chatlink-0.1.1.dist-info/METADATA
atk_training_rin_chatlink-0.1.1.dist-info/WHEEL
atk_training_rin_chatlink-0.1.1.dist-info/entry_points.txt
atk_training_rin_chatlink-0.1.1.dist-info/RECORD
