Metadata-Version: 2.1
Name: atk-training-rin-chatlink
Version: 0.1.1
Summary: Get URLs from a Google Space
Author: nxceurin
Author-email: e20cse376@bennett.edu.in
Requires-Python: >=3.10,<4.0
Classifier: Programming Language :: Python :: 3
Classifier: Programming Language :: Python :: 3.10
Classifier: Programming Language :: Python :: 3.11
Requires-Dist: pyyaml (>=6.0.1,<7.0.0)
